mydates1/Dates.py
mydates1/_initi_.py
mydates1/core.py
mydates1-0.0.1.dist-info/LICENSE
mydates1-0.0.1.dist-info/METADATA
mydates1-0.0.1.dist-info/WHEEL
mydates1-0.0.1.dist-info/top_level.txt
mydates1-0.0.1.dist-info/RECORD
