Metadata-Version: 2.1
Name: mydates1
Version: 0.0.1
Summary: An example of building Python package.
Author: jiangqingliu
Author-email: jiangqingliu822@gmail.com
License: LICENSE
License-File: LICENSE
